README.md
setup.py
bdsim_realtime/__init__.py
bdsim_realtime/record.py
bdsim_realtime/run.py
bdsim_realtime/webapp.py
bdsim_realtime.egg-info/PKG-INFO
bdsim_realtime.egg-info/SOURCES.txt
bdsim_realtime.egg-info/dependency_links.txt
bdsim_realtime.egg-info/requires.txt
bdsim_realtime.egg-info/top_level.txt
bdsim_realtime/../frontend/dist/index.html
bdsim_realtime/../frontend/dist/assets/index-64383812.js
bdsim_realtime/../frontend/dist/assets/index-f0c70c57.css
bdsim_realtime/blocks/__init__.py
bdsim_realtime/blocks/data.py
bdsim_realtime/blocks/displays.py
bdsim_realtime/blocks/functions.py
bdsim_realtime/blocks/io.py
bdsim_realtime/blocks/sources.py
bdsim_realtime/blocks/vision.py
bdsim_realtime/tuning/__init__.py
bdsim_realtime/tuning/parameter.py
bdsim_realtime/tuning/tunable_block.py
bdsim_realtime/tuning/tuners/__init__.py
bdsim_realtime/tuning/tuners/ros_tuner.py
bdsim_realtime/tuning/tuners/tcpclient_tuner.py
bdsim_realtime/tuning/tuners/tuner.py
bdsim_realtime/tuning/tuners/websocket_tuner.py