Metadata-Version: 2.1
Name: bdsim-realtime
Version: 1.0.1
Summary: Real-time execution and remote monitoring and tuning of BDSim Block-Diagrams for modelling and control of Dynamical Systems
Home-page: https://github.com/CallumJHays/bdsim_realtime
Author: Callum Hays
Author-email: callumjhays@gmail.com
License: MIT
Project-URL: Documentation, https://github.com/CallumJHays/bdsim_realtime
Project-URL: Source, https://github.com/CallumJHays/bdsim_realtime
Project-URL: Tracker, https://github.com/CallumJHays/bdsim_realtime/issues
Keywords: python bdsim realtime control remote-control telemetry tuning-interface webapplication tuner signal-analysis control-system block-diagram computation-graph data-flow control-flow rtos simulation modeling computer-vision opencv
Classifier: Development Status :: 4 - Beta
Classifier: Intended Audience :: Developers
Classifier: Intended Audience :: Education
Classifier: Intended Audience :: Science/Research
Classifier: License :: OSI Approved :: MIT License
Classifier: Programming Language :: Python :: 3 :: Only
Requires-Python: >=3.6
Provides-Extra: opencv
